Metadata-Version: 2.1
Name: ccsmeth
Version: 0.4.1
Summary: Detecting DNA methylation from PacBio CCS reads
Home-page: https://github.com/PengNi/ccsmeth
Download-URL: https://github.com/PengNi/ccsmeth/archive/refs/tags/0.4.1.tar.gz
Author: Peng Ni
Author-email: 543943952@qq.com
License: BSD-3-Clause-Clear license
Keywords: methylation,pacbio,neural network
Platform: Linux
Platform: MacOS
Classifier: Programming Language :: Python :: 3
Classifier: Development Status :: 4 - Beta
Classifier: Natural Language :: English
Classifier: License :: OSI Approved :: BSD License
Classifier: Operating System :: MacOS :: MacOS X
Classifier: Operating System :: POSIX :: Linux
License-File: LICENSE
